w_parser/__init__.py
w_parser/w_parser.py
w_parser-0.3.0.dist-info/LICENSE
w_parser-0.3.0.dist-info/WHEEL
w_parser-0.3.0.dist-info/METADATA
w_parser-0.3.0.dist-info/RECORD
